{"metadata":{"usedHelpers":[],"marked":[],"modules":{"imports":[],"exports":{"exported":[],"specifiers":[]}}},"options":{"filename":"/server/dataCreation.js","filenameRelative":"/server/dataCreation.js","env":{},"retainLines":false,"highlightCode":true,"suppressDeprecationMessages":false,"presets":[],"plugins":[[[],null],[[],null],[[],null],[[],null],[[],null],[[],null],[[],null],[[],{"polyfill":false}],[[],null],[[],null],[[],null],[[],null],[[],null],[[],null],[[],null],[[],null],[[],{"loose":true}],[[],{"loose":true}],[[],null],[[],{"loose":true}],[[],null],[[],null],[[],{"allowTopLevelThis":true,"strict":false,"loose":true}],[[],null],[[],null],[[],null],[[],null],[[],null],[[],{"loose":true}],[[],null],[[],null],[[],null],[[],null],[[],null],[[],null],[[],null],[[],null]],"ignore":[],"code":true,"metadata":true,"ast":false,"comments":true,"compact":false,"minified":false,"sourceMap":true,"sourceMaps":true,"sourceMapTarget":"/server/dataCreation.js.map","sourceFileName":"/server/dataCreation.js","babelrc":false,"sourceType":"module","moduleIds":false,"passPerPreset":false,"basename":"dataCreation"},"ignored":false,"code":"","ast":null,"map":{"version":3,"sources":[],"names":[],"mappings":"","file":"/server/dataCreation.js.map","sourcesContent":[]},"hash":"d4272022f5ce93cc9957f7c96dc7686c6b337a30"}
